lanq/__init__.py
lanq/config/__init__.py
lanq/config/config.py
lanq/convert/__init__.py
lanq/convert/base.py
lanq/exec/__init__.py
lanq/exec/base.py
lanq/exec/local.py
lanq/exec/spark.py
lanq/io/__init__.py
lanq/io/export.py
lanq/io/input.py
lanq/io/summary.py
lanq/model/__init__.py
lanq/model/model.py
lanq/model/llm/__init__.py
lanq/model/llm/base.py
lanq/model/llm/gpt.py
lanq/model/llm/llama3.py
lanq/model/llm/perspective.py
lanq/model/llm/common/__init__.py
lanq/model/llm/common/base_llm.py
lanq/model/llm/common/base_llm_api.py
lanq/model/llm/common/openai_api.py
lanq/model/llm/common/turbomind_api.py
lanq/model/rule/__init__.py
lanq/model/rule/base.py
lanq/model/rule/common_rule.py
lanq/model/rule/image_rule.py
lanq/model/rule/prompt_rule.py
lanq/model/rule/util.py
lanq/utils/__init__.py
lanq/utils/log_util/__init__.py
lanq/utils/log_util/logger.py
lanq-2.0.1.dist-info/LICENSE
lanq-2.0.1.dist-info/METADATA
lanq-2.0.1.dist-info/WHEEL
lanq-2.0.1.dist-info/top_level.txt
lanq-2.0.1.dist-info/RECORD
