Metadata-Version: 2.1
Name: lanq
Version: 2.0.1
Summary: Language quality evaluation tool.
Home-page: https://github.com/APX103/Dingo/tree/main
Author: SH AI Lab
Author-email: SHAILab@pjlab.org.cn
Classifier: Programming Language :: Python :: 3
Classifier: Operating System :: OS Independent
Requires-Python: >=3.10
License-File: LICENSE
Requires-Dist: hanziconv
Requires-Dist: jieba
Requires-Dist: jsonlines
Requires-Dist: langid
Requires-Dist: numpy
Requires-Dist: textstat
Requires-Dist: zhon
Requires-Dist: transformers
Requires-Dist: toml
Requires-Dist: pydantic
Requires-Dist: requests
Requires-Dist: Pillow ==9.4.0
Requires-Dist: opencv-python
Requires-Dist: fastapi
Requires-Dist: uvicorn
